{"name":"さんかく","starListLink":"https://ja.wikipedia.org/wiki/%E3%81%95%E3%82%93%E3%81%8B%E3%81%8F%E5%BA%A7%E3%81%AE%E6%81%92%E6%98%9F%E3%81%AE%E4%B8%80%E8%A6%A7","link":"https://ja.wikipedia.org/wiki/さんかく座","stars":[{"名前":"さんかく座β星","バイエル符号":"β","フラムスティード番号":"4","ヘンリー・ドレイパーカタログ":"13161","ヒッパルコス星表":"10064","赤経":"02h 09m 32.6s","赤緯":"+34° 59′ 14.3″","等級 (天文)":"3.00","絶対等級":"0.051","宇宙の距離梯子":"127","スペクトル分類":"A5III","備考":"Deltotum, Deltoton","additional_info":{"星座":"さんかく座","見かけの等級 (mv)":"3.00[1]","分類":"分光連星[1]","赤経 (RA, α)":"02h 09m 32.62712s[1]","赤緯 (Dec, δ)":"+34° 59′ 14.2694″[1]","赤方偏移":"0.000041[1]","視線速度 (Rv)":"12.30 km/s[1]","固有運動 (μ)":"赤経: 149.16 ミリ秒/年[1]赤緯: -39.10 ミリ秒/年[1]","年周視差 (π)":"25.71 ± 0.34ミリ秒[1] （誤差1.3%）","距離":"127 ± 2 光年[注 1] （38.9 ± 0.5 パーセク[注 1]）","絶対等級 (MV)":"0.1[注 2]","半径":"4.4 R☉[2]","質量":"2.5 M☉[2]","スペクトル分類":"A5III [1]","光度":"71 L☉[2]","表面温度":"8,020 K[2]","色指数 (B-V)":"+0.14[3]","色指数 (U-B)":"+0.10[3]","年齢":"5.8億 年[2]","さんかく座4番星[1]BD +34 381[1]FK5 75[1], HD 13161[1]HIP 10064[1], HR 622[1]SAO 55306[1]":""}},{"名前":"さんかく座α星","バイエル符号":"α","フラムスティード番号":"2","ヘンリー・ドレイパーカタログ":"11443","ヒッパルコス星表":"8796","赤経":"01h 53m 04.9s","赤緯":"+29° 34′ 43.8″","等級 (天文)":"3.42","絶対等級":"1.979","宇宙の距離梯子":"63","スペクトル分類":"F5III","備考":"Mothallah, Metallah, Ras al Mothallah, Elmuthalleth, Caput Trianguli","additional_info":{"仮符号・別名":"モサラー,Mothallah[2][3]","星座":"さんかく座","見かけの等級 (mv)":"3.42[1]3.52 - 3.53（変光）[4]","変光星型":"楕円体状変光星(ELL)[4]","分類":"分光連星[1]","赤経 (RA, α)":"01h 53m 04.90710s[1]","赤緯 (Dec, δ)":"+29° 34′ 43.7801″[1]","赤方偏移":"-0.000042[1]","視線速度 (Rv)":"–12.6km/s[1]","固有運動 (μ)":"赤経: 10.82 ミリ秒/年[1]赤緯: –234.24 ミリ秒/年[1]","年周視差 (π)":"51.50 ± 0.23ミリ秒[1] （誤差0.4%）","距離":"63.3 ± 0.3 光年[注 1] （19.42 ± 0.09 パーセク[注 1]）","絶対等級 (MV)":"2.0[注 2]","半径":"3.22 R☉","質量":"1.70 M☉","表面重力":"3.91","自転速度":"81.6km/s","スペクトル分類":"F5III [1]","表面温度":"6,288 K","色指数 (B-V)":"+0.49[5]","色指数 (U-B)":"+0.06[5]","色指数 (R-I)":"+0.28[5]","年齢":"1.6×108年","ラス・アル・ムタラー,Ras al Muthallah,メタラー,Metallah,カプト・トリアングリ,Caput Trianguliさんかく座2番星[1]BD +28 312[1]FK5 64[1], HD 11443[1]HIP 8796[1], HR 544[1]SAO 74996[1]":""}},{"名前":"さんかく座γ星","バイエル符号":"γ","フラムスティード番号":"9","ヘンリー・ドレイパーカタログ":"14055","ヒッパルコス星表":"10670","赤経":"02h 17m 18.84s","赤緯":"+33° 50′ 50.4″","等級 (天文)":"4.03","絶対等級":"1.24","宇宙の距離梯子":"118","スペクトル分類":"A1Vnn","備考":"","additional_info":{"星座":"さんかく座","見かけの等級 (mv)":"4.00[1]","分類":"A型主系列星[1]","赤経 (RA, α)":"02h 17m 18.86703s[1]","赤緯 (Dec, δ)":"+33° 50′ 49.8950″[1]","赤方偏移":"0.000033[1]","視線速度 (Rv)":"9.90 km/s[1]","固有運動 (μ)":"赤経: 44.64 ミリ秒/年[1]赤緯: -52.57 ミリ秒/年[1]","年周視差 (π)":"29.04 ± 0.25ミリ秒[1] （誤差0.9%）","距離":"112.3 ± 1 光年[注 1] （34.4 ± 0.3 パーセク[注 1]）","絶対等級 (MV)":"1.3[注 2]","半径":"1.96 R☉[2]","質量":"2.7 M☉[3]","自転速度":"254 km/s[4]","スペクトル分類":"A1Vnn[1]","光度":"33.0 L☉[3]","表面温度":"9,940 K[5]","色指数 (B-V)":"0.02[6]","色指数 (U-B)":"0.02[6]","年齢":"3億年[3]","さんかく座9番星[1]BD+33 397[1]FK5 79[1]HD 14055[1]HIP 10670[1]HR 664[1]SAO 55427[1]TYC 2318-1875-1[1]2MASS J02171888+3350500[1]":""}},{"名前":"さんかく座δ星","バイエル符号":"δ","フラムスティード番号":"8","ヘンリー・ドレイパーカタログ":"13974","ヒッパルコス星表":"10644","赤経":"02h 17m 02.42s","赤緯":"+34° 13′ 29.4″","等級 (天文)":"4.84","絶対等級":"4.66","宇宙の距離梯子":"35","スペクトル分類":"G0V","備考":"","additional_info":{"星座":"さんかく座","見かけの等級 (mv)":"4.87[1]","赤経 (RA, α)":"02h 17m 03.3016s[1]","赤緯 (Dec, δ)":"+34° 13′ 27.2260″[1]","視線速度 (Rv)":"-6.57 km/s[1]","固有運動 (μ)":"赤経: 1,151.83 ミリ秒/年[1]赤緯: -246.89 ミリ秒/年[1]","年周視差 (π)":"92.73 ± 0.39 ミリ秒[1]","距離":"35.2 光年（10.78 パーセク）","絶対等級 (MV)":"4.71","半径":"0.98 / ? R☉[2]","質量":"1.00 / 0.86 M☉[3]","表面重力":"19.9 / ? g[4]","自転速度":"< 1.5 / ? km/s[4]","スペクトル分類":"G0 Ve / G9 - K4 V[5]","光度":"1.09 / ? L☉[6]","表面温度":"6,215 / 4,493 K[5]","色指数 (B-V)":"0.61","色指数 (U-B)":"0.02","金属量[Fe/H]":"-0.44（太陽比）[4]","年齢":"1.9 ×109[7]","軌道長半径 (a)":"9.80 ± 0.06 ミリ秒[8]（0.106 AU）","離心率 (e)":"0.020 ± 0.005[8]","公転周期 (P)":"10.02 日[8]","軌道傾斜角 (i)":"167 ± 3°[8]","昇交点黄経 (Ω)":"15 ± 9°[8]","前回近点通過":"2,448,117.5 ± 0.2 JD [8]","さんかく座8番星, ADS 1739, BD+33°395, CCDM J02170+3414, GC 2733, GCTP 464.00, グリーゼ 92, HD 13974, HIP 10644, HR 660, LFT 198, LHS 154, LTT 10770, SAO 55420":""}},{"名前":"さんかく座6番星","バイエル符号":"","フラムスティード番号":"6","ヘンリー・ドレイパーカタログ":"13480","ヒッパルコス星表":"10280","赤経":"02h 12m 22.32s","赤緯":"+30° 18′ 11.6″","等級 (天文)":"4.94","絶対等級":"0.08","宇宙の距離梯子":"305","スペクトル分類":"F5V comp SB","備考":"","additional_info":{}},{"名前":"さんかく座14番星","バイエル符号":"","フラムスティード番号":"14","ヘンリー・ドレイパーカタログ":"15656","ヒッパルコス星表":"11784","赤経":"02h 32m 06.14s","赤緯":"+36° 08′ 50.0″","等級 (天文)":"5.15","絶対等級":"−0.25","宇宙の距離梯子":"391","スペクトル分類":"K5III","備考":"","additional_info":{}},{"名前":"さんかく座7番星","バイエル符号":"","フラムスティード番号":"7","ヘンリー・ドレイパーカタログ":"13869","ヒッパルコス星表":"10559","赤経":"02h 15m 56.30s","赤緯":"+33° 21′ 32.3″","等級 (天文)":"5.25","絶対等級":"0.48","宇宙の距離梯子":"293","スペクトル分類":"A0V","備考":"","additional_info":{}},{"名前":"さんかく座10番星","バイエル符号":"","フラムスティード番号":"10","ヘンリー・ドレイパーカタログ":"14252","ヒッパルコス星表":"10793","赤経":"02h 18m 56.99s","赤緯":"+28° 38′ 33.6″","等級 (天文)":"5.29","絶対等級":"0.13","宇宙の距離梯子":"350","スペクトル分類":"A2V","備考":"","additional_info":{}},{"名前":"さんかく座12番星","バイエル符号":"","フラムスティード番号":"12","ヘンリー・ドレイパーカタログ":"15257","ヒッパルコス星表":"11486","赤経":"02h 28m 09.99s","赤緯":"+29° 40′ 10.3″","等級 (天文)":"5.29","絶対等級":"1.90","宇宙の距離梯子":"155","スペクトル分類":"F0III","備考":"","additional_info":{}},{"名前":"さんかく座15番星","バイエル符号":"","フラムスティード番号":"15","ヘンリー・ドレイパーカタログ":"16058","ヒッパルコス星表":"12086","赤経":"02h 35m 46.80s","赤緯":"+34° 41′ 15.7″","等級 (天文)":"5.38","絶対等級":"","宇宙の距離梯子":"","スペクトル分類":"M3III","備考":"","additional_info":{}},{"名前":"さんかく座ε星","バイエル符号":"ε","フラムスティード番号":"3","ヘンリー・ドレイパーカタログ":"12471","ヒッパルコス星表":"9570","赤経":"02h 02m 57.97s","赤緯":"+33° 17′ 02.9″","等級 (天文)":"5.50","絶対等級":"0.22","宇宙の距離梯子":"370","スペクトル分類":"A2V","備考":"連星","additional_info":{}},{"名前":"さんかく座11番星","バイエル符号":"","フラムスティード番号":"11","ヘンリー・ドレイパーカタログ":"15176","ヒッパルコス星表":"11432","赤経":"02h 27m 27.79s","赤緯":"+31° 48′ 04.9″","等級 (天文)":"5.55","絶対等級":"0.83","宇宙の距離梯子":"286","スペクトル分類":"K1III:","備考":"","additional_info":{}},{"名前":"","バイエル符号":"","フラムスティード番号":"","ヘンリー・ドレイパーカタログ":"10390","ヒッパルコス星表":"7943","赤経":"01h 42m 03.45s","赤緯":"+35° 14′ 44.8″","等級 (天文)":"5.63","絶対等級":"1.13","宇宙の距離梯子":"259","スペクトル分類":"B9IV-V","備考":"","additional_info":{}},{"名前":"","バイエル符号":"","フラムスティード番号":"","ヘンリー・ドレイパーカタログ":"11007","ヒッパルコス星表":"8433","赤経":"01h 48m 41.68s","赤緯":"+32° 41′ 22.2″","等級 (天文)":"5.78","絶対等級":"3.60","宇宙の距離梯子":"89","スペクトル分類":"F8V","備考":"","additional_info":{}},{"名前":"","バイエル符号":"","フラムスティード番号":"","ヘンリー・ドレイパーカタログ":"11928","ヒッパルコス星表":"9132","赤経":"01h 57m 43.74s","赤緯":"+27° 48′ 16.3″","等級 (天文)":"5.84","絶対等級":"0.02","宇宙の距離梯子":"476","スペクトル分類":"M2III","備考":"","additional_info":{}},{"名前":"","バイエル符号":"","フラムスティード番号":"","ヘンリー・ドレイパーカタログ":"15755","ヒッパルコス星表":"11840","赤経":"02h 32m 52.66s","赤緯":"+34° 32′ 32.8″","等級 (天文)":"5.84","絶対等級":"1.33","宇宙の距離梯子":"260","スペクトル分類":"K0III","備考":"","additional_info":{}},{"名前":"さんかく座13番星","バイエル符号":"","フラムスティード番号":"13","ヘンリー・ドレイパーカタログ":"15335","ヒッパルコス星表":"11548","赤経":"02h 28m 48.54s","赤緯":"+29° 55′ 53.7″","等級 (天文)":"5.89","絶対等級":"3.45","宇宙の距離梯子":"100","スペクトル分類":"G0V","備考":"","additional_info":{}},{"名前":"","バイエル符号":"","フラムスティード番号":"","ヘンリー・ドレイパーカタログ":"10348","ヒッパルコス星表":"7906","赤経":"01h 41m 39.24s","赤緯":"+30° 02′ 49.7″","等級 (天文)":"5.97","絶対等級":"−0.06","宇宙の距離梯子":"523","スペクトル分類":"K0III","備考":"","additional_info":{}},{"名前":"","バイエル符号":"","フラムスティード番号":"","ヘンリー・ドレイパーカタログ":"16187","ヒッパルコス星表":"12160","赤経":"02h 36m 43.05s","赤緯":"+31° 36′ 27.6″","等級 (天文)":"6.07","絶対等級":"0.36","宇宙の距離梯子":"452","スペクトル分類":"K0","備考":"","additional_info":{}},{"名前":"","バイエル符号":"","フラムスティード番号":"","ヘンリー・ドレイパーカタログ":"16220","ヒッパルコス星表":"12200","赤経":"02h 37m 06.51s","赤緯":"+32° 53′ 27.7″","等級 (天文)":"6.23","絶対等級":"2.52","宇宙の距離梯子":"180","スペクトル分類":"F8V","備考":"","additional_info":{}},{"名前":"さんかく座5番星","バイエル符号":"","フラムスティード番号":"5","ヘンリー・ドレイパーカタログ":"13372","ヒッパルコス星表":"10220","赤経":"02h 11m 25.00s","赤緯":"+31° 31′ 35.1″","等級 (天文)":"6.24","絶対等級":"0.39","宇宙の距離梯子":"482","スペクトル分類":"A1m","備考":"","additional_info":{}},{"名前":"","バイエル符号":"","フラムスティード番号":"","ヘンリー・ドレイパーカタログ":"15464","ヒッパルコス星表":"11651","赤経":"02h 30m 16.56s","赤緯":"+33° 50′ 01.8″","等級 (天文)":"6.26","絶対等級":"0.98","宇宙の距離梯子":"371","スペクトル分類":"K1III","備考":"","additional_info":{}},{"名前":"","バイエル符号":"","フラムスティード番号":"","ヘンリー・ドレイパーカタログ":"10588","ヒッパルコス星表":"8086","赤経":"01h 43m 50.15s","赤緯":"+32° 11′ 31.2″","等級 (天文)":"6.32","絶対等級":"0.57","宇宙の距離梯子":"460","スペクトル分類":"G8III-IV SB","備考":"","additional_info":{}},{"名前":"","バイエル符号":"","フラムスティード番号":"","ヘンリー・ドレイパーカタログ":"13747","ヒッパルコス星表":"10446","赤経":"02h 14m 37.88s","赤緯":"+28° 41′ 29.1″","等級 (天文)":"6.35","絶対等級":"2.48","宇宙の距離梯子":"194","スペクトル分類":"K1III","備考":"","additional_info":{}},{"名前":"","バイエル符号":"","フラムスティード番号":"","ヘンリー・ドレイパーカタログ":"9298","ヒッパルコス星表":"7147","赤経":"01h 32m 07.58s","赤緯":"+34° 47′ 59.9″","等級 (天文)":"6.39","絶対等級":"−0.90","宇宙の距離梯子":"937","スペクトル分類":"B7IIIMNp...","備考":"","additional_info":{}},{"名前":"HD 13189","バイエル符号":"","フラムスティード番号":"","ヘンリー・ドレイパーカタログ":"13189","ヒッパルコス星表":"10085","赤経":"02h 09m 40.17s","赤緯":"+32° 18′ 59.2″","等級 (天文)":"7.57","絶対等級":"1.23","宇宙の距離梯子":"602","スペクトル分類":"K3II","備考":"太陽系外惑星または褐色矮星 (b)","additional_info":{}},{"名前":"HD 9446","バイエル符号":"","フラムスティード番号":"","ヘンリー・ドレイパーカタログ":"9446","ヒッパルコス星表":"7245","赤経":"01h 33m 20.18s","赤緯":"+29° 15′ 54.5″","等級 (天文)":"8.35","絶対等級":"4.74","宇宙の距離梯子":"172","スペクトル分類":"G5V","備考":"太陽系外惑星 (b & c)","additional_info":{"星座":"さんかく座","見かけの等級 (mv)":"8.35","赤経 (RA, α)":"01h 33m 20.18561s[1]","赤緯 (Dec, δ)":"+29° 15′ 54.5375″[1]","視線速度 (Rv)":"20.2 km/s[1]","固有運動 (μ)":"赤経: 192.01 ミリ秒/年赤緯: -53.99 ミリ秒/年[1]","年周視差 (π)":"19.10 ± 1.06ミリ秒[1] （誤差5.5%）","距離":"171 ± 9 光年[注 1] （52 ± 3 パーセク[注 1]）","絶対等級 (MV)":"4.85[2]","惑星の数":"2","半径":"1.0 R☉[2]","質量":"1.0 ± 0.1 M☉[2]","表面重力":"4.53 ± 0.16 (log g)[2]","自転速度":"4 ± 1 km/s[2]","スペクトル分類":"G5V[1]","光度":"1.1 L☉[2]","表面温度":"5,793 ± 22 K[2]","色指数 (B-V)":"0.680[2]","金属量[Fe/H]":"0.09 ± 0.05[2]","BD+28 253, HIP 7245, SAO 74788":""}},{"名前":"さんかく座X星","バイエル符号":"","フラムスティード番号":"","ヘンリー・ドレイパーカタログ":"12211","ヒッパルコス星表":"9383","赤経":"02h 00m 33.72s","赤緯":"+27° 53′ 19.3″","等級 (天文)":"8.86","絶対等級":"2.76","宇宙の距離梯子":"541","スペクトル分類":"A7V","備考":"","additional_info":{}}],"info":{"属格形":"Trianguli","略符":"Tri","発音":"英語発音: [traɪˈæŋɡjʊləm]、属格:/traɪˈæŋɡjʊlaɪ/","象徴":"The Triangle","概略位置：赤経":"2","概略位置：赤緯":"+30","広さ":"132平方度 （78位）","主要恒星数":"3","バイエル符号/フラムスティード番号を持つ恒星数":"15","系外惑星が確認されている恒星数":"0","3.0等より明るい恒星数":"1","10パーセク以内にある恒星数":"1","最輝星":"β Tri（3.00等）","最も近い星":"δ Tri;（35.4光年）","メシエ天体数":"1","隣接する星座":"アンドロメダ座うお座おひつじ座ペルセウス座"}}
